nntool/__init__.py
nntool/version.py
nntool/experiment/__init__.py
nntool/experiment/config.py
nntool/experiment/utils.py
nntool/slurm/__init__.py
nntool/slurm/config.py
nntool/slurm/function.py
nntool/slurm/task.py
nntool/slurm/utils.py
nntool/slurm/wrap.py
nntool/slurm/accelerator/__init__.py
nntool/slurm/accelerator/utils.py
nntool/slurm/core/__init__.py
nntool/slurm/core/_slurm.py
nntool/slurm/core/_slurm_context.py
nntool/slurm/parser/__init__.py
nntool/slurm/parser/parse.py
nntool/utils/__init__.py
nntool/wandb/__init__.py
nntool/wandb/config.py
nntool-2.0.2.dist-info/licenses/LICENSE
nntool-2.0.2.dist-info/METADATA
nntool-2.0.2.dist-info/WHEEL
nntool-2.0.2.dist-info/top_level.txt
nntool-2.0.2.dist-info/RECORD
