Metadata-Version: 2.4
Name: nntool
Version: 2.0.2
Summary: nntool is a package designed to provide seamless Python function execution on Slurm for machine learning research, with useful utilities for experiment tracking and management.
Author-email: Junhao Liu <junhaoliu17@gmail.com>
License: MIT License
Project-URL: Homepage, https://github.com/jhliu17/nntool
Keywords: deep learning,neural network,research
Classifier: License :: OSI Approved :: MIT License
Requires-Python: >=3.10
License-File: LICENSE
Requires-Dist: tyro
Requires-Dist: submitit>=1.5.4
Requires-Dist: wandb>=0.15.0
Requires-Dist: tomli>=2.0.1
Dynamic: license-file
